<?xml version="1.0" encoding="UTF-8"?>
<config>
	<endpoint>
		<description>Service to retrieve a single position resource
		</description>
		<verbs>SOURCE</verbs>
		<grammar>
			<active>
				<identifier>active:position</identifier>
				<argument name="businessArea" desc="Business area partition to which position belongs" />
				<argument name="location" desc="Owning business location of position" />
				<argument name="lifecycleType" desc="Position transaction lifecycle type" />
				<argument name="accountUUID" desc="Position Account UUID" />
				<argument name="positionType" desc="Position calculation type" />
				<argument name="positionDate" desc="Record date of position" />
				<argument name="positionSymbol" desc="Instrument symbol of position" />
			</active>
		</grammar>
		<request>
			<identifier>res:/dummy
			</identifier>
		</request>
	</endpoint>
</config>
